Metadata-Version: 1.1
Name: simdna
Version: 0.4.2
Summary: Simulated datasets of DNA
Home-page: UNKNOWN
Author: UNKNOWN
Author-email: UNKNOWN
License: UNKNOWN
Download-URL: https://github.com/kundajelab/simdna
Platform: UNKNOWN
